talia/__init__.py
talia/utils/__init__.py
talia/utils/parser.py
talia-1.0.0.dist-info/LICENSE
talia-1.0.0.dist-info/METADATA
talia-1.0.0.dist-info/WHEEL
talia-1.0.0.dist-info/top_level.txt
talia-1.0.0.dist-info/RECORD
