Metadata-Version: 2.1
Name: talia
Version: 1.0.0
Summary: Talia is a powerful open-source chess engine that plays different variants of chess.
Author-email: Ariana Hejazyan <arianahejazyan@gmail.com>, Fatemeh Bouzari <fatemehfnb26@gmail.com>
Project-URL: Homepage, https://github.com/arianahejazyan/chess-engine
Project-URL: Issues, https://github.com/arianahejazyan/chess-engine/issues
Classifier: Programming Language :: Python :: 3
Classifier: License :: OSI Approved :: MIT License
Classifier: Operating System :: OS Independent
Requires-Python: >=3.11
License-File: LICENSE
